LICENSE
MANIFEST.in
README.md
propyte.py
propyte_alert.py
propyte_loop_alert_on_new_users.py
setup.py
propyte.egg-info/PKG-INFO
propyte.egg-info/SOURCES.txt
propyte.egg-info/dependency_links.txt
propyte.egg-info/entry_points.txt
propyte.egg-info/requires.txt
propyte.egg-info/top_level.txt