Metadata-Version: 1.0
Name: propyte
Version: 2018.1.18.1628
Summary: template Python program
Home-page: https://github.com/wdbm/propyte
Author: Will Breaden Madden
Author-email: wbm@protonmail.ch
License: GPLv3
Platform: UNKNOWN
